[{"line":1,"elements":[{"line":3,"name":"","description":"","type":"background","keyword":"Background","steps":[{"result":{"duration":483744700,"status":"passed"},"line":4,"name":"user open \"paradize\" site","match":{"arguments":[{"val":"\"paradize\"","offset":10}],"location":"steps.LoginSteps.user_open_site(java.lang.String)"},"keyword":"Given "},{"result":{"duration":31303076000,"status":"passed"},"line":5,"name":"user login as \"conceptor\"","match":{"arguments":[{"val":"\"conceptor\"","offset":14}],"location":"steps.LoginSteps.user_login_as(java.lang.String)"},"keyword":"When "}]},{"start_timestamp":"2025-10-27T09:34:20.669Z","before":[{"result":{"duration":3146487300,"status":"passed"},"match":{"location":"hooks.Hooks.setup()"}}],"line":7,"name":"Conceptor creates a draft cek fisik","description":"","id":"create-draft;conceptor-creates-a-draft-cek-fisik","type":"scenario","keyword":"Scenario","steps":[{"result":{"duration":1320001900,"status":"passed"},"line":8,"name":"access cek fisik","match":{"location":"steps.DraftParadizeSteps.accessCekFisik()"},"keyword":"When "},{"result":{"duration":1009832800,"status":"passed"},"line":9,"name":"user fill in draft header","match":{"location":"steps.DraftParadizeSteps.user_fill_in_draft_header()"},"keyword":"Then "},{"result":{"duration":97610100,"status":"passed"},"line":10,"name":"click next","match":{"location":"steps.DraftParadizeSteps.clickNext()"},"keyword":"When "},{"result":{"duration":6319706000,"status":"passed"},"line":11,"name":"choose asset number","match":{"location":"steps.DraftParadizeSteps.chooseAssetNumber()"},"keyword":"Then "},{"result":{"duration":243985600,"status":"passed"},"line":12,"name":"choose klasifikasi asset","match":{"location":"steps.DraftParadizeSteps.chooseKlasifikasiAsset()"},"keyword":"And "},{"result":{"duration":254255300,"status":"passed"},"line":13,"name":"choose status cek fisik","match":{"location":"steps.DraftParadizeSteps.chooseStatusCekFisik()"},"keyword":"And "},{"result":{"duration":82866400,"status":"passed"},"line":14,"name":"fill keterangan","match":{"location":"steps.DraftParadizeSteps.fillKeterangan()"},"keyword":"And "},{"result":{"duration":37969500,"status":"passed"},"line":15,"name":"upload document","match":{"location":"steps.DraftParadizeSteps.uploadDocument()"},"keyword":"And "},{"result":{"duration":63584500,"status":"passed"},"line":16,"name":"add asset","match":{"location":"steps.DraftParadizeSteps.addAsset()"},"keyword":"Then "},{"result":{"duration":1360519500,"status":"passed"},"line":17,"name":"click next","match":{"location":"steps.DraftParadizeSteps.clickNext()"},"keyword":"When "},{"result":{"duration":25928411500,"status":"passed"},"line":18,"name":"choose approver","match":{"location":"steps.DraftParadizeSteps.chooseApprover()"},"keyword":"Then "},{"result":{"duration":59530600,"status":"passed"},"line":19,"name":"submit request","match":{"location":"steps.DraftParadizeSteps.submitRequest()"},"keyword":"Then "}]}],"name":"Create Draft","description":"","id":"create-draft","keyword":"Feature","uri":"file:src/test/resources/features/paradize/cekfisik/DraftParadize.feature","tags":[]}]